ewccli/__init__.py
ewccli/configuration.py
ewccli/enums.py
ewccli/ewccli.py
ewccli/logger.py
ewccli/utils.py
ewccli/backends/__init__.py
ewccli/backends/ansible/__init__.py
ewccli/backends/ansible/backend_ansible.py
ewccli/backends/kubernetes/__init__.py
ewccli/backends/kubernetes/backend_k8s.py
ewccli/backends/kubernetes/exceptions.py
ewccli/backends/kubernetes/utils.py
ewccli/backends/kubernetes/CRDtemplates/__init__.py
ewccli/backends/kubernetes/CRDtemplates/bucketccrd.py
ewccli/backends/kubernetes/CRDtemplates/clustercrd.py
ewccli/backends/kubernetes/CRDtemplates/commoncrd.py
ewccli/backends/kubernetes/CRDtemplates/dnscrd.py
ewccli/backends/openstack/__init__.py
ewccli/backends/openstack/backend_ostack.py
ewccli/commands/__init__.py
ewccli/commands/commons.py
ewccli/commands/commons_infra.py
ewccli/commands/dns_command.py
ewccli/commands/infra_command.py
ewccli/commands/k8s_command.py
ewccli/commands/login_command.py
ewccli/commands/s3_command.py
ewccli/commands/hub/__init__.py
ewccli/commands/hub/hub_backends.py
ewccli/commands/hub/hub_command.py
ewccli/commands/hub/hub_utils.py
ewccli/tests/__init__.py
ewccli/tests/ewccli_base_test.py
ewccli/tests/ewccli_commands_common_infra_test.py
ewccli/tests/ewccli_commands_hub_deploy_server_test.py
ewccli/tests/ewccli_commands_hub_inputs_validation_test.py
ewccli/tests/ewccli_config_test.py
ewccli/tests/ewccli_core_test.py
ewccli/tests/ewccli_download_items_test.py
ewccli/tests/ewccli_infra_test.py
ewccli/tests/ewccli_login_test.py
ewccli/tests/ewccli_ssh_keys_test.py
ewccli/tests/test_dns_utils.py
ewccli-0.2.0.dist-info/METADATA
ewccli-0.2.0.dist-info/WHEEL
ewccli-0.2.0.dist-info/entry_points.txt
ewccli-0.2.0.dist-info/licenses/AUTHORS
ewccli-0.2.0.dist-info/licenses/LICENSE
ewccli-0.2.0.dist-info/RECORD
