Metadata-Version: 2.4
Name: ewccli
Version: 0.2.0
Summary: Python package to handle EWC resources.
Project-URL: Homepage, https://www.europeanweather.cloud/
Project-URL: Bug Tracker, https://github.com/ewcloud/ewccli/issues
Project-URL: Documentation, https://github.com/ewcloud/ewccli/blob/main/README.md
Project-URL: Source Code, https://github.com/ewcloud/ewccli
Project-URL: Organization, https://www.europeanweather.cloud/
Project-URL: Release Notes, https://github.com/ewcloud/ewccli/blob/main/CHANGELOG.md
Author-email: EWC <support@europeanweather.cloud>
Maintainer-email: EWC <support@europeanweather.cloud>
License:                     GNU GENERAL PUBLIC LICENSE
License-File: AUTHORS
License-File: LICENSE
Classifier: Development Status :: 2 - Pre-Alpha
Classifier: Intended Audience :: Science/Research
Classifier: License :: OSI Approved :: GNU General Public License v3 or later (GPLv3+)
Classifier: Operating System :: OS Independent
Classifier: Programming Language :: Python
Classifier: Topic :: Scientific/Engineering
Requires-Python: >3.10
Requires-Dist: ansible-runner==2.4.0
Requires-Dist: ansible==11.8.0
Requires-Dist: click==8.3.0
Requires-Dist: cryptography==46.0.2
Requires-Dist: kubernetes==34.1.0
Requires-Dist: prompt-toolkit==3.0.52
Requires-Dist: python-openstackclient==8.2.0
Requires-Dist: pyyaml==6.0.3
Requires-Dist: requests==2.32.5
Requires-Dist: rich-click==1.9.2
Requires-Dist: rich==14.1.0
Provides-Extra: test
Requires-Dist: coverage==7.10.5; extra == 'test'
Requires-Dist: pre-commit==4.3.0; extra == 'test'
Requires-Dist: pydantic==2.11.7; extra == 'test'
Requires-Dist: pydeps==3.0.1; extra == 'test'
Requires-Dist: pytest-html==4.1.1; extra == 'test'
Requires-Dist: pytest-mock==3.14.1; extra == 'test'
Requires-Dist: pytest==8.4.1; extra == 'test'
Requires-Dist: sphinx-click==6.0.0; extra == 'test'
Requires-Dist: sphinx-rtd-theme==3.0.2; extra == 'test'
Requires-Dist: sphinx==8.1.3; extra == 'test'
